methylbert/__init__.py
methylbert/cli.py
methylbert/config.py
methylbert/deconvolute.py
methylbert/function.py
methylbert/network.py
methylbert/trainer.py
methylbert/utils.py
methylbert/data/__init__.py
methylbert/data/bam.py
methylbert/data/dataset.py
methylbert/data/finetune_data_generate.py
methylbert/data/genome.py
methylbert/data/vocab.py
methylbert-2.0.2.dist-info/LICENSE
methylbert-2.0.2.dist-info/METADATA
methylbert-2.0.2.dist-info/WHEEL
methylbert-2.0.2.dist-info/entry_points.txt
methylbert-2.0.2.dist-info/top_level.txt
methylbert-2.0.2.dist-info/RECORD
