Metadata-Version: 2.2
Name: methylbert
Version: 2.0.2
Summary: A Transformer-based model for read-level DNA methylation pattern identification and tumour deconvolution
Author-email: Yunhee Jeong <y.jeong@dkfz-heidelberg.de>
License: MIT License
Requires-Python: >=3.11
License-File: LICENSE
Requires-Dist: biopython==1.84
Requires-Dist: matplotlib==3.9.2
Requires-Dist: numpy==2.1.1
Requires-Dist: pandas==2.2.2
Requires-Dist: pysam==0.22.1
Requires-Dist: scikit-learn==1.5.1
Requires-Dist: scipy==1.14.1
Requires-Dist: torch==2.4.1
Requires-Dist: tqdm==4.66.5
Requires-Dist: transformers==4.44.2
Requires-Dist: tokenizers==0.19.1
Requires-Dist: urllib3==2.2.2
Requires-Dist: zipp==3.13.0
